kinto_pusher/__init__.py
kinto_pusher/listener.py
kinto_pusher-1.0.0.dist-info/LICENSE
kinto_pusher-1.0.0.dist-info/METADATA
kinto_pusher-1.0.0.dist-info/WHEEL
kinto_pusher-1.0.0.dist-info/top_level.txt
kinto_pusher-1.0.0.dist-info/RECORD
