Metadata-Version: 2.1
Name: kinto-pusher
Version: 1.0.0
Summary: Plug Kinto notifications into Pusher.com
Home-page: https://github.com/Kinto/kinto-pusher
Author: Mathieu Leplatre
Author-email: mathieu@leplat.re
License: Apache License (2.0)
Keywords: kinto pusher
Platform: UNKNOWN
Classifier: Development Status :: 2 - Pre-Alpha
Classifier: Intended Audience :: Developers
Classifier: License :: OSI Approved :: Apache Software License
Classifier: Programming Language :: Python :: 3
Classifier: Programming Language :: Python :: 3.6
Classifier: Programming Language :: Python :: 3.7
Requires-Dist: kinto
Requires-Dist: pusher
